[
    {
        "data": [
            {
                "allowDdcCi": true,
                "allowSdrSoftwareBrightness": false,
                "autoRotation": "InTabletMode",
                "brightness": 0.3433583959899749,
                "colorPowerTradeoff": "PreferEfficiency",
                "colorProfileSource": "sRGB",
                "connectorName": "eDP-1",
                "detectedDdcCi": false,
                "edidHash": "6ee9da0202bf6841f53bd3f1cf3b3bc9",
                "edidIdentifier": "SDC 16800 0 0 2022 0",
                "edrPolicy": "always",
                "highDynamicRange": false,
                "iccProfilePath": "",
                "maxBitsPerColor": 0,
                "mode": {
                    "height": 1200,
                    "refreshRate": 60003,
                    "width": 1920
                },
                "overscan": 0,
                "rgbRange": "Automatic",
                "scale": 1,
                "sdrBrightness": 400,
                "sdrGamutWideness": 0,
                "transform": "Normal",
                "uuid": "3fd67534-76a5-45fb-8929-b94c59e96754",
                "vrrPolicy": "Never",
                "wideColorGamut": false
            },
            {
                "allowDdcCi": true,
                "allowSdrSoftwareBrightness": false,
                "autoRotation": "InTabletMode",
                "brightness": 1,
                "colorPowerTradeoff": "PreferEfficiency",
                "colorProfileSource": "sRGB",
                "connectorName": "DP-1",
                "detectedDdcCi": true,
                "edidHash": "5bdc35ec5197c167266c0cf41cb52116",
                "edidIdentifier": "AUS 10088 160659 39 2022 0",
                "edrPolicy": "always",
                "highDynamicRange": false,
                "iccProfilePath": "",
                "maxBitsPerColor": 0,
                "mode": {
                    "height": 2160,
                    "refreshRate": 59997,
                    "width": 3840
                },
                "overscan": 0,
                "rgbRange": "Automatic",
                "scale": 2,
                "sdrBrightness": 322,
                "sdrGamutWideness": 0,
                "transform": "Normal",
                "uuid": "9c948e01-4e63-4b5e-893e-23ff15c887be",
                "vrrPolicy": "Never",
                "wideColorGamut": false
            },
            {
                "allowDdcCi": true,
                "allowSdrSoftwareBrightness": false,
                "autoRotation": "InTabletMode",
                "brightness": 1,
                "colorPowerTradeoff": "PreferEfficiency",
                "colorProfileSource": "sRGB",
                "connectorName": "DP-1",
                "detectedDdcCi": true,
                "edidHash": "ab35a9590c1cd5d54c583e0c22e07d42",
                "edidIdentifier": "ACR 1853 276943997 8 2021 0",
                "edrPolicy": "always",
                "highDynamicRange": false,
                "iccProfilePath": "",
                "maxBitsPerColor": 0,
                "mode": {
                    "height": 1080,
                    "refreshRate": 164995,
                    "width": 1920
                },
                "overscan": 0,
                "rgbRange": "Automatic",
                "scale": 0.875,
                "sdrBrightness": 322,
                "sdrGamutWideness": 0,
                "transform": "Normal",
                "uuid": "a12d1ca2-5d42-470f-8aec-53e33cdb8712",
                "vrrPolicy": "Never",
                "wideColorGamut": false
            }
        ],
        "name": "outputs"
    },
    {
        "data": [
            {
                "lidClosed": false,
                "outputs": [
                    {
                        "enabled": true,
                        "outputIndex": 0,
                        "position": {
                            "x": 0,
                            "y": 0
                        },
                        "priority": 0,
                        "replicationSource": ""
                    },
                    {
                        "enabled": true,
                        "outputIndex": 1,
                        "position": {
                            "x": 1920,
                            "y": 0
                        },
                        "priority": 1,
                        "replicationSource": ""
                    }
                ]
            },
            {
                "lidClosed": false,
                "outputs": [
                    {
                        "enabled": true,
                        "outputIndex": 0,
                        "position": {
                            "x": 0,
                            "y": 0
                        },
                        "priority": 0,
                        "replicationSource": ""
                    },
                    {
                        "enabled": true,
                        "outputIndex": 1,
                        "position": {
                            "x": 1920,
                            "y": 0
                        },
                        "priority": 1,
                        "replicationSource": ""
                    },
                    {
                        "enabled": true,
                        "outputIndex": 2,
                        "position": {
                            "x": 3840,
                            "y": 0
                        },
                        "priority": 2,
                        "replicationSource": ""
                    }
                ]
            },
            {
                "lidClosed": true,
                "outputs": [
                    {
                        "enabled": false,
                        "outputIndex": 0,
                        "position": {
                            "x": 0,
                            "y": 0
                        },
                        "priority": -1,
                        "replicationSource": ""
                    },
                    {
                        "enabled": true,
                        "outputIndex": 1,
                        "position": {
                            "x": 0,
                            "y": 0
                        },
                        "priority": 1,
                        "replicationSource": ""
                    },
                    {
                        "enabled": true,
                        "outputIndex": 2,
                        "position": {
                            "x": 1920,
                            "y": 0
                        },
                        "priority": 0,
                        "replicationSource": ""
                    }
                ]
            },
            {
                "lidClosed": true,
                "outputs": [
                    {
                        "enabled": false,
                        "outputIndex": 0,
                        "position": {
                            "x": 0,
                            "y": 0
                        },
                        "priority": -1,
                        "replicationSource": ""
                    },
                    {
                        "enabled": true,
                        "outputIndex": 1,
                        "position": {
                            "x": 0,
                            "y": 0
                        },
                        "priority": 0,
                        "replicationSource": ""
                    }
                ]
            },
            {
                "lidClosed": false,
                "outputs": [
                    {
                        "enabled": true,
                        "outputIndex": 0,
                        "position": {
                            "x": 0,
                            "y": 0
                        },
                        "priority": 0,
                        "replicationSource": ""
                    },
                    {
                        "enabled": true,
                        "outputIndex": 2,
                        "position": {
                            "x": 0,
                            "y": 0
                        },
                        "priority": 1,
                        "replicationSource": "3fd67534-76a5-45fb-8929-b94c59e96754"
                    }
                ]
            },
            {
                "lidClosed": true,
                "outputs": [
                    {
                        "enabled": false,
                        "outputIndex": 0,
                        "position": {
                            "x": 0,
                            "y": 0
                        },
                        "priority": -1,
                        "replicationSource": ""
                    },
                    {
                        "enabled": true,
                        "outputIndex": 2,
                        "position": {
                            "x": 0,
                            "y": 0
                        },
                        "priority": 0,
                        "replicationSource": "3fd67534-76a5-45fb-8929-b94c59e96754"
                    }
                ]
            },
            {
                "lidClosed": true,
                "outputs": [
                    {
                        "enabled": true,
                        "outputIndex": 0,
                        "position": {
                            "x": 0,
                            "y": 0
                        },
                        "priority": 0,
                        "replicationSource": ""
                    }
                ]
            },
            {
                "lidClosed": false,
                "outputs": [
                    {
                        "enabled": true,
                        "outputIndex": 0,
                        "position": {
                            "x": 0,
                            "y": 0
                        },
                        "priority": 0,
                        "replicationSource": ""
                    }
                ]
            }
        ],
        "name": "setups"
    }
]
